livedownload/__init__.py
livedownload/main.py
livedownload/downloader/__init__.py
livedownload/downloader/aiodown.py
livedownload/parsers/__init__.py
livedownload/parsers/bilibili.py
livedownload-1.1.3.dist-info/LICENSE
livedownload-1.1.3.dist-info/METADATA
livedownload-1.1.3.dist-info/WHEEL
livedownload-1.1.3.dist-info/entry_points.txt
livedownload-1.1.3.dist-info/top_level.txt
livedownload-1.1.3.dist-info/RECORD
