Metadata-Version: 2.1
Name: livedownload
Version: 1.1.3
Summary: UNKNOWN
Home-page: https://github.com/LiveDownload/LiveDownload
License: GNU General Public License v3
Keywords: LiveDownload,bilibili
Platform: UNKNOWN
Requires-Python: >=3.6
Requires-Dist: Click (>=7.0)
Requires-Dist: aiohttp (<4.0,>=3.6.2)
Requires-Dist: colorlog (>=4.1.0)
Requires-Dist: dataclasses (>=0.7) ; python_version < "3.7"
